datamask/.mypy_cache/3.8/@plugins_snapshot.json
datamask/.mypy_cache/3.8/_ast.data.json
datamask/.mypy_cache/3.8/_ast.meta.json
datamask/.mypy_cache/3.8/_csv.data.json
datamask/.mypy_cache/3.8/_csv.meta.json
datamask/.mypy_cache/3.8/_importlib_modulespec.data.json
datamask/.mypy_cache/3.8/_importlib_modulespec.meta.json
datamask/.mypy_cache/3.8/_random.data.json
datamask/.mypy_cache/3.8/_random.meta.json
datamask/.mypy_cache/3.8/_thread.data.json
datamask/.mypy_cache/3.8/_thread.meta.json
datamask/.mypy_cache/3.8/abc.data.json
datamask/.mypy_cache/3.8/abc.meta.json
datamask/.mypy_cache/3.8/argparse.data.json
datamask/.mypy_cache/3.8/argparse.meta.json
datamask/.mypy_cache/3.8/array.data.json
datamask/.mypy_cache/3.8/array.meta.json
datamask/.mypy_cache/3.8/ast.data.json
datamask/.mypy_cache/3.8/ast.meta.json
datamask/.mypy_cache/3.8/builtins.data.json
datamask/.mypy_cache/3.8/builtins.meta.json
datamask/.mypy_cache/3.8/codecs.data.json
datamask/.mypy_cache/3.8/codecs.meta.json
datamask/.mypy_cache/3.8/collections/__init__.data.json
datamask/.mypy_cache/3.8/collections/__init__.meta.json
datamask/.mypy_cache/3.8/collections/abc.data.json
datamask/.mypy_cache/3.8/collections/abc.meta.json
datamask/.mypy_cache/3.8/concurrent/__init__.data.json
datamask/.mypy_cache/3.8/concurrent/__init__.meta.json
datamask/.mypy_cache/3.8/concurrent/futures/__init__.data.json
datamask/.mypy_cache/3.8/concurrent/futures/__init__.meta.json
datamask/.mypy_cache/3.8/concurrent/futures/_base.data.json
datamask/.mypy_cache/3.8/concurrent/futures/_base.meta.json
datamask/.mypy_cache/3.8/concurrent/futures/process.data.json
datamask/.mypy_cache/3.8/concurrent/futures/process.meta.json
datamask/.mypy_cache/3.8/concurrent/futures/thread.data.json
datamask/.mypy_cache/3.8/concurrent/futures/thread.meta.json
datamask/.mypy_cache/3.8/csv.data.json
datamask/.mypy_cache/3.8/csv.meta.json
datamask/.mypy_cache/3.8/ctypes/__init__.data.json
datamask/.mypy_cache/3.8/ctypes/__init__.meta.json
datamask-2.0.0.dist-info/WHEEL
datamask-2.0.0.dist-info/METADATA
datamask-2.0.0.dist-info/entry_points.txt
datamask-2.0.0.dist-info/RECORD
