Metadata-Version: 2.1
Name: datamask
Version: 2.0.0
Summary: Data PII cleaning/masking for databases
Home-page: https://github.com/haard/datamask
License: MIT
Author: Fredrik Håård
Author-email: fredrik@metallapan.se
Requires-Python: >=3.7,<4
Classifier: License :: OSI Approved :: MIT License
Classifier: Programming Language :: Python :: 3
Classifier: Programming Language :: Python :: 3.7
Classifier: Programming Language :: Python :: 3.8
Classifier: Programming Language :: Python :: 3.9
Classifier: Programming Language :: Python :: 3.10
Classifier: Programming Language :: Python :: 3.11
Requires-Dist: Faker (>8.12.0,<9.0.0)
Requires-Dist: psycopg2-binary (>2.8.0,<2.10)
Requires-Dist: python-slugify (>4.0.0,<9.0.0)
